complexaudio-1.0.4.dist-info/METADATA
complexaudio-1.0.4.dist-info/RECORD
complexaudio-1.0.4.dist-info/WHEEL
complexaudio-1.0.4.dist-info/top_level.txt
simpleaudio/__init__.py
simpleaudio/_simpleaudio.cp36-win32.pyd
simpleaudio/functionchecks.py
simpleaudio/shiny.py
simpleaudio/test_audio/c.wav
simpleaudio/test_audio/e.wav
simpleaudio/test_audio/g.wav
simpleaudio/test_audio/left_right.wav
simpleaudio/test_audio/notes_2_16_44.wav
